NRSS/__init__.py
NRSS/_version.py
NRSS/checkH5.py
NRSS/morphology.py
NRSS/reader.py
NRSS/visualizer.py
NRSS/writer.py
NRSS/cmap/__init__.py
NRSS/cmap/infinitydouble_cmap.npy
NRSS_tutorials/__init__.py
NRSS_tutorials/3D_polymer_adsorption/01_polymer_adsorption_model.ipynb
NRSS_tutorials/3D_polymer_adsorption/02_polymer_adsorption_functions.ipynb
NRSS_tutorials/3D_polymer_adsorption/03_polymer_adsorption_sweeps.ipynb
NRSS_tutorials/3D_polymer_adsorption/04_polymer_adsorption_sweep_streamlined.ipynb
NRSS_tutorials/3D_polymer_adsorption/05_visualizing_simulation_results.ipynb
NRSS_tutorials/3D_polymer_adsorption/06_visualizing_sweeps_of_sweeps.ipynb
NRSS_tutorials/3D_polymer_adsorption/Euler_ZYZ-v2.gif
NRSS_tutorials/3D_polymer_adsorption/Euler_ZYZ-v4.gif
NRSS_tutorials/3D_polymer_adsorption/PS_anisotropic_milner_July2024.txt
NRSS_tutorials/3D_polymer_adsorption/globe.gif
NRSS_tutorials/3D_polymer_adsorption/pmma_dan.txt
NRSS_tutorials/3D_polymer_adsorption/polymer_adsorption_functions01.py
NRSS_tutorials/3D_polymer_adsorption/siox_iso_NIST_Jan2024.txt
NRSS_tutorials/3D_polymer_adsorption/pickles/.gitignore
NRSS_tutorials/3D_polymer_adsorption/videos/.gitignore
NRSS_tutorials/MWCNTs/HOPG_TEY.nc
NRSS_tutorials/MWCNTs/ParamSweepPlotting.ipynb
NRSS_tutorials/MWCNTs/RSA.gif
NRSS_tutorials/MWCNTs/env.yml
NRSS_tutorials/MWCNTs/nb1_rsoxs.ipynb
NRSS_tutorials/MWCNTs/nb2_nexafs.ipynb
NRSS_tutorials/MWCNTs/nb3_nrss.ipynb
NRSS_tutorials/MWCNTs/reference_frame.png
NRSS_tutorials/MWCNTs/Figures/A_comparison.png
NRSS_tutorials/MWCNTs/Figures/ExperimentA.pdf
NRSS_tutorials/MWCNTs/Figures/HOPG_TEY.pdf
NRSS_tutorials/MWCNTs/Figures/SampleTransmission.pdf
NRSS_tutorials/MWCNTs/Figures/SampleTransmittance.pdf
NRSS_tutorials/MWCNTs/Figures/deltabeta.pdf
NRSS_tutorials/MWCNTs/Figures/deltabeta2.pdf
NRSS_tutorials/MWCNTs/Figures/experiment2D.png
NRSS_tutorials/MWCNTs/Figures/experimentISI.pdf
NRSS_tutorials/MWCNTs/Figures/experimental1D.pdf
nrss-2025.7.25.1.dist-info/licenses/LICENSE
nrss-2025.7.25.1.dist-info/METADATA
nrss-2025.7.25.1.dist-info/WHEEL
nrss-2025.7.25.1.dist-info/top_level.txt
nrss-2025.7.25.1.dist-info/RECORD
