Metadata-Version: 2.4
Name: NRSS
Version: 2025.7.25.1
Summary: NIST RSoXS Simulation Suite
Author-email: Dean DeLongchamp <dean.delongchamp@nist.gov>, Peter Dudenas <peter.dudenas@nist.gov>
License: This software was developed by employees of the National Institute of Standards
Project-URL: Homepage, https://github.com/usnistgov/NRSS/
Classifier: Development Status :: 3 - Alpha
Classifier: Intended Audience :: Science/Research
Classifier: License :: Public Domain
Classifier: Operating System :: POSIX :: Linux
Classifier: Topic :: Scientific/Engineering :: Physics
Classifier: Programming Language :: Python :: 3
License-File: LICENSE
Requires-Dist: h5py
Requires-Dist: matplotlib
Requires-Dist: numpy
Requires-Dist: pandas
Requires-Dist: PyHyperScattering>=0.1.7
Requires-Dist: scikit-image
Requires-Dist: scipy
Dynamic: license-file
